{
  "urn": "100279",
  "name": "Stoke Newington School and Sixth Form",
  "address": "Clissold Road",
  "locality": "",
  "address3": "Hackney",
  "town": "London",
  "county": "",
  "postcode": "N16 9EX",
  "minimum_age": "11",
  "maximum_age": "19",
  "easting": "532879",
  "northing": "186072",
  "url": "http://www.sns.hackney.sch.uk/",
  "phase": "Secondary",
  "type": "Local authority maintained schools",
  "detailed_type": "Community school",
  "lat": "51.557887",
  "lng": "-0.084609060"
}
