{
  "urn": "101048",
  "name": "St Mary's RC Voluntary Aided Primary School",
  "address": "7 St Joseph's Street",
  "locality": "Battersea",
  "address3": "",
  "town": "London",
  "county": "",
  "postcode": "SW8 4BE",
  "minimum_age": "4",
  "maximum_age": "11",
  "easting": "528837",
  "northing": "176954",
  "url": "www.stmarysschoolbattersea.co.uk",
  "phase": "Primary",
  "type": "LA maintained schools",
  "detailed_type": "Voluntary aided school",
  "lat": "51.476883",
  "lng": "-0.14621170"
}
