{
  "urn": "101324",
  "name": "St Mary's CofE Primary School, East Barnet",
  "address": "Littlegrove",
  "locality": "East Barnet",
  "address3": "",
  "town": "Barnet",
  "county": "Hertfordshire",
  "postcode": "EN4 8SR",
  "minimum_age": "4",
  "maximum_age": "11",
  "easting": "527317",
  "northing": "195180",
  "url": "www.stmarysen4-barnet.co.uk",
  "phase": "Primary",
  "type": "Local authority maintained schools",
  "detailed_type": "Voluntary aided school",
  "lat": "51.641020",
  "lng": "-0.16149309"
}
