{
  "urn": "101787",
  "name": "All Saints CofE Primary School",
  "address": "Upper Beulah Hill",
  "locality": "Upper Norwood",
  "address3": "",
  "town": "London",
  "county": "",
  "postcode": "SE19 3LG",
  "minimum_age": "3",
  "maximum_age": "11",
  "easting": "533166",
  "northing": "169871",
  "url": "www.allsaintsschoolcroydon.org/",
  "phase": "Primary",
  "type": "Local authority maintained schools",
  "detailed_type": "Voluntary aided school",
  "lat": "51.412230",
  "lng": "-0.086575907"
}
