{
  "urn": "103422",
  "name": "Abbey Catholic Primary School",
  "address": "Sutton Road",
  "locality": "",
  "address3": "Erdington",
  "town": "Birmingham",
  "county": "West Midlands",
  "postcode": "B23 6QL",
  "minimum_age": "4",
  "maximum_age": "11",
  "easting": "411283",
  "northing": "292402",
  "url": "www.abbeyrc.bham.sch.uk",
  "phase": "Primary",
  "type": "Local authority maintained schools",
  "detailed_type": "Voluntary aided school",
  "lat": "52.529373",
  "lng": "-1.8351122"
}
