{
  "urn": "103456",
  "name": "St Teresa's Catholic Primary School",
  "address": "Butlers Road",
  "locality": "Handsworth Wood",
  "address3": "",
  "town": "Birmingham",
  "county": "West Midlands",
  "postcode": "B20 2NY",
  "minimum_age": "4",
  "maximum_age": "11",
  "easting": "405328",
  "northing": "290997",
  "url": "http://www.stteresa.bham.sch.uk",
  "phase": "Primary",
  "type": "LA maintained schools",
  "detailed_type": "Voluntary aided school",
  "lat": "52.516832",
  "lng": "-1.9229144"
}
