{
  "urn": "104101",
  "name": "St George and St Teresa Catholic Primary School",
  "address": "Mill Lane",
  "locality": "Bentley Heath",
  "address3": "",
  "town": "Solihull",
  "county": "West Midlands",
  "postcode": "B93 8PA",
  "minimum_age": "3",
  "maximum_age": "11",
  "easting": "417138",
  "northing": "275732",
  "url": "www.stgandt.solihull.sch.uk/",
  "phase": "Primary",
  "type": "Local authority maintained schools",
  "detailed_type": "Voluntary aided school",
  "lat": "52.379360",
  "lng": "-1.7496570"
}
