{
  "urn": "104290",
  "name": "Bushbury Hill Primary School",
  "address": "Old Fallings Lane",
  "locality": "",
  "address3": "",
  "town": "Wolverhampton",
  "county": "West Midlands",
  "postcode": "WV10 8BY",
  "minimum_age": "3",
  "maximum_age": "11",
  "easting": "392771",
  "northing": "302195",
  "url": "www.bushburyhillprimary.uk/",
  "phase": "Primary",
  "type": "Local authority maintained schools",
  "detailed_type": "Community school",
  "lat": "52.617475",
  "lng": "-2.1082076"
}
