{
  "urn": "104309",
  "name": "Palmers Cross Primary School",
  "address": "Windermere Road",
  "locality": "Tettenhall",
  "address3": "",
  "town": "Wolverhampton",
  "county": "West Midlands",
  "postcode": "WV6 9DF",
  "minimum_age": "5",
  "maximum_age": "11",
  "easting": "388824",
  "northing": "301822",
  "url": "www.palmerscrossprimaryschool.co.uk/",
  "phase": "Primary",
  "type": "Local authority maintained schools",
  "detailed_type": "Community school",
  "lat": "52.614054",
  "lng": "-2.1664925"
}
