{
  "urn": "105211",
  "name": "Blackrod Anglican/Methodist Primary School",
  "address": "Vicarage Road West",
  "locality": "Blackrod",
  "address3": "",
  "town": "Bolton",
  "county": "Lancashire",
  "postcode": "BL6 5DE",
  "minimum_age": "3",
  "maximum_age": "11",
  "easting": "361120",
  "northing": "410842",
  "url": "www.blackrodchurchschool.com",
  "phase": "Primary",
  "type": "Local authority maintained schools",
  "detailed_type": "Voluntary controlled school",
  "lat": "53.592703",
  "lng": "-2.5888785"
}
