{
  "urn": "105581",
  "name": "The Barlow RC High School and Specialist Science College",
  "address": "Parrs Wood Road",
  "locality": "East Didsbury",
  "address3": "",
  "town": "Manchester",
  "county": "",
  "postcode": "M20 6BX",
  "minimum_age": "11",
  "maximum_age": "16",
  "easting": "385470",
  "northing": "390981",
  "url": "http://www.thebarlowrchigh.co.uk/",
  "phase": "Secondary",
  "type": "LA maintained schools",
  "detailed_type": "Voluntary aided school",
  "lat": "53.415431",
  "lng": "-2.2200724"
}
