{
  "urn": "107334",
  "name": "Our Lady and St Brendan's Catholic Primary School",
  "address": "The Bank",
  "locality": "Idle",
  "address3": "",
  "town": "Bradford",
  "county": "West Yorkshire",
  "postcode": "BD10 0QA",
  "minimum_age": "4",
  "maximum_age": "11",
  "easting": "418674",
  "northing": "436513",
  "url": "www.ourladyandstbrendans.co.uk/",
  "phase": "Primary",
  "type": "LA maintained schools",
  "detailed_type": "Voluntary aided school",
  "lat": "53.824555",
  "lng": "-1.7177982"
}
