{
  "urn": "107730",
  "name": "Birkenshaw Church of England Voluntary Controlled Primary School",
  "address": "Station Lane",
  "locality": "Birkenshaw",
  "address3": "",
  "town": "Bradford",
  "county": "West Yorkshire",
  "postcode": "BD11 2JE",
  "minimum_age": "3",
  "maximum_age": "11",
  "easting": "420564",
  "northing": "428855",
  "url": "http://www.birkenshawprimary.org.uk",
  "phase": "Primary",
  "type": "LA maintained schools",
  "detailed_type": "Voluntary controlled school"
}
