{
  "urn": "109665",
  "name": "Hastingsbury Business & Enterprise College",
  "address": "Hill Rise",
  "locality": "Kempston",
  "address3": "",
  "town": "Bedford",
  "county": "Bedfordshire",
  "postcode": "MK42 7EB",
  "minimum_age": "13",
  "maximum_age": "18",
  "easting": "502194",
  "northing": "246782",
  "url": "http://www.hastingsbury.beds.sch.uk",
  "phase": "Secondary",
  "type": "LA maintained schools",
  "detailed_type": "Foundation school",
  "lat": "52.109933",
  "lng": "-0.50914756"
}
