{
  "urn": "113410",
  "name": "Exbourne Church of England Primary School",
  "address": "Exbourne",
  "locality": "",
  "address3": "",
  "town": "Okehampton",
  "county": "Devon",
  "postcode": "EX20 3SQ",
  "minimum_age": "4",
  "maximum_age": "11",
  "easting": "260259",
  "northing": "101903",
  "url": "www.exbourne-primary.devon.sch.uk",
  "phase": "Primary",
  "type": "Local authority maintained schools",
  "detailed_type": "Voluntary controlled school",
  "lat": "50.799791",
  "lng": "-3.9843420"
}
