{
  "urn": "113421",
  "name": "Bickleigh on Exe Church of England Primary School",
  "address": "Bell Meadow",
  "locality": "Bickleigh",
  "address3": "",
  "town": "Tiverton",
  "county": "Devon",
  "postcode": "EX16 8RE",
  "minimum_age": "4",
  "maximum_age": "11",
  "easting": "294024",
  "northing": "107126",
  "url": "http://www.bickleigh.ik.org",
  "phase": "Primary",
  "type": "LA maintained schools",
  "detailed_type": "Voluntary controlled school",
  "lat": "50.853909",
  "lng": "-3.5069208"
}
