{
  "urn": "113434",
  "name": "Webber's Church of England Primary School",
  "address": "Holcombe Rogus",
  "locality": "",
  "address3": "",
  "town": "Wellington",
  "county": "Somerset",
  "postcode": "TA21 0PE",
  "minimum_age": "4",
  "maximum_age": "11",
  "easting": "305776",
  "northing": "118906",
  "url": "www.webbers.devon.sch.uk",
  "phase": "Primary",
  "type": "Local authority maintained schools",
  "detailed_type": "Voluntary aided school",
  "lat": "50.961846",
  "lng": "-3.3430626"
}
