{
  "urn": "113734",
  "name": "Christchurch Infant School",
  "address": "Addiscombe Road",
  "locality": "",
  "address3": "",
  "town": "Christchurch",
  "county": "Dorset",
  "postcode": "BH23 2AE",
  "minimum_age": "5",
  "maximum_age": "7",
  "easting": "415156",
  "northing": "93379",
  "url": "http://www.christchurchinf.dorset.sch.uk/",
  "phase": "Primary",
  "type": "Local authority maintained schools",
  "detailed_type": "Community school",
  "lat": "50.739826",
  "lng": "-1.7865793"
}
