{
  "urn": "113975",
  "name": "Seaham Harbour Nursery School",
  "address": "Bottleworks Road",
  "locality": "Seaham Harbour",
  "address3": "",
  "town": "Seaham",
  "county": "County Durham",
  "postcode": "SR7 7NN",
  "minimum_age": "2",
  "maximum_age": "5",
  "easting": "443202",
  "northing": "548814",
  "url": "www.seahamharbour.durham.sch.uk",
  "phase": "Nursery",
  "type": "Local authority maintained schools",
  "detailed_type": "Local authority nursery school",
  "lat": "54.832300",
  "lng": "-1.3289792"
}
