{
  "urn": "115630",
  "name": "King's Stanley Church of England Junior School",
  "address": "Church Street",
  "locality": "King's Stanley",
  "address3": "",
  "town": "Stonehouse",
  "county": "Gloucestershire",
  "postcode": "GL10 3HZ",
  "minimum_age": "7",
  "maximum_age": "11",
  "easting": "381232",
  "northing": "203635",
  "url": "http://www.kingsstanley.ik.org",
  "phase": "Primary",
  "type": "Local authority maintained schools",
  "detailed_type": "Voluntary controlled school",
  "lat": "51.731111",
  "lng": "-2.2731521"
}
