{
  "urn": "116269",
  "name": "Andover Church of England Primary School",
  "address": "East Street",
  "locality": "",
  "address3": "",
  "town": "Andover",
  "county": "Hampshire",
  "postcode": "SP10 1EP",
  "minimum_age": "4",
  "maximum_age": "11",
  "easting": "436732",
  "northing": "145430",
  "url": "www.andover-pri.hants.sch.uk",
  "phase": "Primary",
  "type": "Local authority maintained schools",
  "detailed_type": "Voluntary controlled school",
  "lat": "51.206904",
  "lng": "-1.4755788"
}
