{
  "urn": "116360",
  "name": "Andrews' Endowed Church of England Primary School",
  "address": "92 London Road",
  "locality": "Holybourne",
  "address3": "",
  "town": "Alton",
  "county": "Hampshire",
  "postcode": "GU34 4EL",
  "minimum_age": "4",
  "maximum_age": "11",
  "easting": "473206",
  "northing": "140843",
  "url": "www.andrewsendowed.co.uk/",
  "phase": "Primary",
  "type": "LA maintained schools",
  "detailed_type": "Voluntary aided school",
  "lat": "51.162162",
  "lng": "-0.95447238"
}
