{
  "urn": "116378",
  "name": "Our Lady and St Joseph Catholic Primary School",
  "address": "83a Ramley Road",
  "locality": "Pennington",
  "address3": "",
  "town": "Lymington",
  "county": "Hampshire",
  "postcode": "SO41 8GY",
  "minimum_age": "4",
  "maximum_age": "11",
  "easting": "430339",
  "northing": "95671",
  "url": "www.olsjschool.co.uk",
  "phase": "Primary",
  "type": "Local authority maintained schools",
  "detailed_type": "Voluntary aided school",
  "lat": "50.759845",
  "lng": "-1.5712276"
}
