{
  "urn": "118041",
  "name": "St Bernadette's Catholic Primary School",
  "address": "Anne's Crescent",
  "locality": "Ashby",
  "address3": "",
  "town": "Scunthorpe",
  "county": "Lincolnshire",
  "postcode": "DN16 2LW",
  "minimum_age": "3",
  "maximum_age": "11",
  "easting": "490489",
  "northing": "408959",
  "url": "http://lincolnshire.schooljotter.com/stbernadettes",
  "phase": "Primary",
  "type": "Local authority maintained schools",
  "detailed_type": "Voluntary aided school",
  "lat": "53.569444",
  "lng": "-0.63506783"
}
