{
  "urn": "118199",
  "name": "St Thomas of Canterbury Catholic Primary School",
  "address": "High Street",
  "locality": "Carisbrooke",
  "address3": "",
  "town": "Newport",
  "county": "Isle of Wight",
  "postcode": "PO30 1NR",
  "minimum_age": "5",
  "maximum_age": "11",
  "easting": "448721",
  "northing": "88270",
  "url": "www.stthomasofcantrcpri.iow.sch.uk/",
  "phase": "Primary",
  "type": "LA maintained schools",
  "detailed_type": "Voluntary aided school",
  "lat": "50.692046",
  "lng": "-1.3116043"
}
