{
  "urn": "118230",
  "name": "Beaver Education Project At Beaver Centre",
  "address": "135 Beaver Lane",
  "locality": "South Ashford",
  "address3": "",
  "town": "Ashford",
  "county": "Kent",
  "postcode": "TN23 5NX",
  "minimum_age": "11",
  "maximum_age": "16",
  "easting": "599851",
  "northing": "141358",
  "url": "http://www.beaver-ed-project.kent.sch.uk",
  "phase": "Not applicable",
  "type": "Local authority maintained schools",
  "detailed_type": "Pupil referral unit",
  "lat": "51.136607",
  "lng": "0.85529760"
}
