{
  "urn": "118219",
  "name": "Mayfield Church of England Voluntary Controlled Middle School",
  "address": "St Vincent's Road",
  "locality": "",
  "address3": "",
  "town": "Ryde",
  "county": "Isle of Wight",
  "postcode": "PO33 3PT",
  "minimum_age": "9",
  "maximum_age": "13",
  "easting": "458255",
  "northing": "92113",
  "url": "http://www.mayfieldmiddle.iow.sch.uk",
  "phase": "Middle deemed secondary",
  "type": "Local authority maintained schools",
  "detailed_type": "Voluntary controlled school",
  "lat": "50.725727",
  "lng": "-1.1760367"
}
