{
  "urn": "118598",
  "name": "Bidborough Church of England Voluntary Controlled Primary School",
  "address": "Spring Lane",
  "locality": "Bidborough",
  "address3": "",
  "town": "Tunbridge Wells",
  "county": "Kent",
  "postcode": "TN3 0UE",
  "minimum_age": "4",
  "maximum_age": "11",
  "easting": "556545",
  "northing": "143127",
  "url": "http://www.bidborough.kent.sch.uk",
  "phase": "Primary",
  "type": "Local authority maintained schools",
  "detailed_type": "Voluntary controlled school",
  "lat": "51.165971",
  "lng": "0.23762448"
}
