{
  "urn": "118782",
  "name": "St Mary's Catholic Primary School",
  "address": "Greenfield Road",
  "locality": "",
  "address3": "",
  "town": "Gillingham",
  "county": "Kent",
  "postcode": "ME7 1YH",
  "minimum_age": "3",
  "maximum_age": "11",
  "easting": "577917",
  "northing": "168572",
  "url": "www.stmarysrcp.medway.sch.uk/",
  "phase": "Primary",
  "type": "Local authority maintained schools",
  "detailed_type": "Voluntary aided school",
  "lat": "51.388299",
  "lng": "0.55565305"
}
