{
  "urn": "119325",
  "name": "Lancaster Lane Community Primary School",
  "address": "Hunters Road",
  "locality": "Clayton-le-Woods",
  "address3": "",
  "town": "Leyland",
  "county": "Lancashire",
  "postcode": "PR25 5TT",
  "minimum_age": "4",
  "maximum_age": "11",
  "easting": "355835",
  "northing": "422177",
  "url": "www.lancasterlane-school.ik.org",
  "phase": "Primary",
  "type": "LA maintained schools",
  "detailed_type": "Community school",
  "lat": "53.694157",
  "lng": "-2.6703337"
}
