{
  "urn": "119693",
  "name": "Heyhouses Endowed Church of England Primary School",
  "address": "Clarendon Road North",
  "locality": "St Anne's",
  "address3": "",
  "town": "Lytham St Annes",
  "county": "Lancashire",
  "postcode": "FY8 3EE",
  "minimum_age": "4",
  "maximum_age": "11",
  "easting": "332858",
  "northing": "429609",
  "url": "www.heyhouses.lancs.sch.uk/",
  "phase": "Primary",
  "type": "Local authority maintained schools",
  "detailed_type": "Voluntary aided school",
  "lat": "53.758493",
  "lng": "-3.0198740"
}
