{
  "urn": "120273",
  "name": "Kibworth High School & Community Technology College",
  "address": "Smeeton Road",
  "locality": "Kibworth",
  "address3": "",
  "town": "Leicester",
  "county": "Leicestershire",
  "postcode": "LE8 0LG",
  "minimum_age": "11",
  "maximum_age": "14",
  "easting": "468127",
  "northing": "293369",
  "url": "http://www.kibworthhigh.leics.sch.uk/",
  "phase": "Secondary",
  "type": "Local authority maintained schools",
  "detailed_type": "Community school",
  "lat": "52.533935",
  "lng": "-0.99708020"
}
