{
  "urn": "120610",
  "name": "The Saint Augustine's Catholic Primary School, Stamford",
  "address": "Kesteven Road",
  "locality": "",
  "address3": "",
  "town": "Stamford",
  "county": "Lincolnshire",
  "postcode": "PE9 1SR",
  "minimum_age": "4",
  "maximum_age": "11",
  "easting": "503108",
  "northing": "308217",
  "url": "http://www.st-augustine.lincs.sch.uk",
  "phase": "Primary",
  "type": "LA maintained schools",
  "detailed_type": "Voluntary aided school",
  "lat": "52.661878",
  "lng": "-0.47692204"
}
