{
  "urn": "121056",
  "name": "Sporle Voluntary Controlled Primary School",
  "address": "82 The Street",
  "locality": "Sporle",
  "address3": "",
  "town": "King's Lynn",
  "county": "Norfolk",
  "postcode": "PE32 2DR",
  "minimum_age": "5",
  "maximum_age": "11",
  "easting": "584924",
  "northing": "311531",
  "url": "www.narvalleyfederation.co.uk/",
  "phase": "Primary",
  "type": "Local authority maintained schools",
  "detailed_type": "Voluntary controlled school",
  "lat": "52.669933",
  "lng": "0.73346793"
}
