{
  "urn": "121490",
  "name": "Eppleby Forcett Church of England Primary School",
  "address": "Eppleby",
  "locality": "",
  "address3": "",
  "town": "Richmond",
  "county": "North Yorkshire",
  "postcode": "DL11 7AY",
  "minimum_age": "2",
  "maximum_age": "11",
  "easting": "417743",
  "northing": "513203",
  "url": "http://www.ef-mtschools.co.uk",
  "phase": "Primary",
  "type": "Local authority maintained schools",
  "detailed_type": "Voluntary controlled school",
  "lat": "54.513823",
  "lng": "-1.7274525"
}
