{
  "urn": "122295",
  "name": "Humshaugh Church of England First School",
  "address": "Humshaugh",
  "locality": "",
  "address3": "",
  "town": "Hexham",
  "county": "Northumberland",
  "postcode": "NE46 4AA",
  "minimum_age": "3",
  "maximum_age": "9",
  "easting": "391952",
  "northing": "571038",
  "url": "http://www.humshaugh.northumberland.sch.uk/",
  "phase": "Primary",
  "type": "Local authority maintained schools",
  "detailed_type": "Voluntary aided school",
  "lat": "55.033797",
  "lng": "-2.1274485"
}
