{
  "urn": "122352",
  "name": "Glendale Middle School",
  "address": "15 Brewery Lane",
  "locality": "",
  "address3": "",
  "town": "Wooler",
  "county": "Northumberland",
  "postcode": "NE71 6QF",
  "minimum_age": "9",
  "maximum_age": "13",
  "easting": "399599",
  "northing": "627857",
  "url": "http://www.glendale.northumberland.sch.uk/",
  "phase": "Middle deemed secondary",
  "type": "LA maintained schools",
  "detailed_type": "Community school",
  "lat": "55.544423",
  "lng": "-2.0079125"
}
