{
  "urn": "122452",
  "name": "John T Rice Infant and Nursery School",
  "address": "Braemar Road",
  "locality": "Forest Town",
  "address3": "",
  "town": "Mansfield",
  "county": "Nottinghamshire",
  "postcode": "NG19 0LL",
  "minimum_age": "3",
  "maximum_age": "7",
  "easting": "458034",
  "northing": "363109",
  "url": "www.johntrice.notts.sch.uk/",
  "phase": "Primary",
  "type": "LA maintained schools",
  "detailed_type": "Community school",
  "lat": "53.161951",
  "lng": "-1.1334657"
}
