{
  "urn": "122669",
  "name": "Radcliffe-on-Trent Infant and Nursery School",
  "address": "Bingham Road",
  "locality": "Radcliffe-on-Trent",
  "address3": "",
  "town": "Nottingham",
  "county": "Nottinghamshire",
  "postcode": "NG12 2FU",
  "minimum_age": "3",
  "maximum_age": "7",
  "easting": "465227",
  "northing": "339257",
  "url": "www.rotins.notts.sch.uk/",
  "phase": "Primary",
  "type": "Local authority maintained schools",
  "detailed_type": "Community school",
  "lat": "52.946743",
  "lng": "-1.0307207"
}
