{
  "urn": "123489",
  "name": "Newport Church of England Voluntary Controlled Junior School",
  "address": "Avenue Road",
  "locality": "",
  "address3": "",
  "town": "Newport",
  "county": "Shropshire",
  "postcode": "TF10 7EA",
  "minimum_age": "7",
  "maximum_age": "11",
  "easting": "374711",
  "northing": "318793",
  "url": "",
  "phase": "Primary",
  "type": "Local authority maintained schools",
  "detailed_type": "Voluntary controlled school",
  "lat": "52.766138",
  "lng": "-2.3762343"
}
