{
  "urn": "123833",
  "name": "St Benedict's Church of England Voluntary Aided Junior School",
  "address": "Benedict Street",
  "locality": "",
  "address3": "",
  "town": "Glastonbury",
  "county": "Somerset",
  "postcode": "BA6 9EX",
  "minimum_age": "7",
  "maximum_age": "11",
  "easting": "349729",
  "northing": "138869",
  "url": "www.stbenedictsjuniorschoolglastonbury.org/",
  "phase": "Primary",
  "type": "LA maintained schools",
  "detailed_type": "Voluntary aided school",
  "lat": "51.146864",
  "lng": "-2.7200550"
}
