{
  "urn": "124263",
  "name": "The Henry Prince CofE (C) First School",
  "address": "Main Road",
  "locality": "Mayfield",
  "address3": "",
  "town": "Ashbourne",
  "county": "Derbyshire",
  "postcode": "DE6 2LB",
  "minimum_age": "3",
  "maximum_age": "9",
  "easting": "415561",
  "northing": "345478",
  "url": "www.henryprince.staffs.sch.uk/",
  "phase": "Primary",
  "type": "Local authority maintained schools",
  "detailed_type": "Voluntary controlled school",
  "lat": "53.006393",
  "lng": "-1.7695498"
}
