{
  "urn": "124412",
  "name": "Clayton Hall Business and Language College",
  "address": "Clayton Lane",
  "locality": "Clayton",
  "address3": "",
  "town": "Newcastle-under-Lyme",
  "county": "Staffordshire",
  "postcode": "ST5 3DN",
  "minimum_age": "11",
  "maximum_age": "16",
  "easting": "385402",
  "northing": "343521",
  "url": "http://www.claytonhall.org.uk/",
  "phase": "Secondary",
  "type": "LA maintained schools",
  "detailed_type": "Foundation school",
  "lat": "52.988822",
  "lng": "-2.2189083"
}
