{
  "urn": "131309",
  "name": "Trinity and St Michael's VA CofE/Methodist Primary School",
  "address": "Out Lane",
  "locality": "Croston",
  "address3": "",
  "town": "Leyland",
  "county": "Lancashire",
  "postcode": "PR26 9HJ",
  "minimum_age": "4",
  "maximum_age": "11",
  "easting": "349166",
  "northing": "418676",
  "url": "www.croston-pri.lancs.sch.uk/",
  "phase": "Primary",
  "type": "LA maintained schools",
  "detailed_type": "Voluntary aided school",
  "lat": "53.662085",
  "lng": "-2.7707481"
}
