{
  "urn": "131582",
  "name": "Young People's Centre",
  "address": "Western School Site",
  "locality": "Cambridge Road",
  "address3": "",
  "town": "Grimsby",
  "county": "North East Lincolnshire",
  "postcode": "DN34 5TD",
  "minimum_age": "14",
  "maximum_age": "16",
  "easting": "524712",
  "northing": "408332",
  "url": "",
  "phase": "Not applicable",
  "type": "Local authority maintained schools",
  "detailed_type": "Pupil referral unit",
  "lat": "53.556803",
  "lng": "-0.11880689"
}
