{
  "urn": "131837",
  "name": "Our Lady and St Philomena's Catholic Primary School",
  "address": "Sparrow Hall Road",
  "locality": "",
  "address3": "",
  "town": "Liverpool",
  "county": "Merseyside",
  "postcode": "L9 6BU",
  "minimum_age": "3",
  "maximum_age": "11",
  "easting": "338574",
  "northing": "395670",
  "url": "http://www.olasp.co.uk",
  "phase": "Primary",
  "type": "LA maintained schools",
  "detailed_type": "Voluntary aided school",
  "lat": "53.454188",
  "lng": "-2.9264861"
}
