{
  "urn": "135059",
  "name": "Wolverley Sebright VA Primary School",
  "address": "Franche Road",
  "locality": "Wolverley",
  "address3": "",
  "town": "Kidderminster",
  "county": "Worcestershire",
  "postcode": "DY11 5TP",
  "minimum_age": "5",
  "maximum_age": "11",
  "easting": "382782",
  "northing": "279205",
  "url": "www.wolverleysebright.co.uk",
  "phase": "Primary",
  "type": "Local authority maintained schools",
  "detailed_type": "Voluntary aided school",
  "lat": "52.410572",
  "lng": "-2.2545475"
}
