{
  "urn": "135246",
  "name": "Our Lady Star of the Sea Catholic Primary School",
  "address": "Capenhurst Lane",
  "locality": "",
  "address3": "",
  "town": "ELLESMERE PORT",
  "county": "Cheshire",
  "postcode": "CH65 7AQ",
  "minimum_age": "3",
  "maximum_age": "11",
  "easting": "339219",
  "northing": "375295",
  "url": "www.ourladystar.cheshire.sch.uk",
  "phase": "Primary",
  "type": "Local authority maintained schools",
  "detailed_type": "Voluntary aided school",
  "lat": "53.271143",
  "lng": "-2.9128508"
}
