{
  "urn": "135693",
  "name": "OneSchool Global UK Reading Campus",
  "address": "401 Old Whitley Wood Lane",
  "locality": "Shinfield",
  "address3": "",
  "town": "Reading",
  "county": "Berkshire",
  "postcode": "RG2 8QA",
  "minimum_age": "7",
  "maximum_age": "11",
  "easting": "472596",
  "northing": "168724",
  "url": "www.readingprimary.focus-school.com",
  "phase": "Not applicable",
  "type": "Independent schools",
  "detailed_type": "Other independent school",
  "lat": "51.412898",
  "lng": "-0.95753556"
}
