{
  "urn": "137967",
  "name": "Horbury Bridge Church of England Junior and Infant Academy",
  "address": "Bridge Road",
  "locality": "Horbury Bridge",
  "address3": "",
  "town": "Wakefield",
  "county": "West Yorkshire",
  "postcode": "WF4 5PS",
  "minimum_age": "3",
  "maximum_age": "11",
  "easting": "428084",
  "northing": "418077",
  "url": "www.horburybridgeacademy.co.uk",
  "phase": "Primary",
  "type": "Academies",
  "detailed_type": "Academy converter",
  "lat": "53.658435",
  "lng": "-1.5765188"
}
