{
  "urn": "146371",
  "name": "Monksmoor Park Church of England Primary School",
  "address": "Croxden Way",
  "locality": "",
  "address3": "",
  "town": "Daventry",
  "county": "Northamptonshire",
  "postcode": "NN11 2PD",
  "minimum_age": "4",
  "maximum_age": "11",
  "easting": "458176",
  "northing": "264630",
  "url": "www.monksmoorceprimary.co.uk",
  "phase": "Primary",
  "type": "LA maintained schools",
  "detailed_type": "Voluntary aided school",
  "lat": "52.276749",
  "lng": "-1.1487477"
}
